watchdata.py
watchdata-0.1.dist-info/METADATA
watchdata-0.1.dist-info/WHEEL
watchdata-0.1.dist-info/licenses/LICENSE
watchdata-0.1.dist-info/RECORD
