Metadata-Version: 2.1
Name: watchdata
Version: 0.1
Summary: Open-source library containing database about series/animes and including a built-in utility.
Project-URL: Github, https://github.com/swarthur/watchdata
Project-URL: Bug, https://github.com/swarthur/watchdata/issues
Author: swarthur
License-Expression: MIT
License-File: LICENSE
Classifier: License :: OSI Approved :: MIT License
Classifier: Operating System :: OS Independent
Classifier: Programming Language :: Python :: 3
Requires-Python: >=3.11
